<annotation>
  <folder>VOC2007</folder>
  <filename>339.jpg</filename>
  <source>
    <database>Coco database</database>
  </source>
  <size>
    <width>266</width>
    <height>190</height>
    <depth>3</depth>
  </size>
  <segmented>0</segmented>
  <object>
    <name>bird</name>
    <pose>Unspecified</pose>
    <truncated>0</truncated>
    <difficult>0</difficult>
    <bndbox>
      <xmin>23</xmin>
      <ymin>1</ymin>
      <xmax>204</xmax>
      <ymax>190</ymax>
    </bndbox>
  </object>
</annotation>
